Metadata-Version: 2.1
Name: namematch
Version: 1.2.1
Summary: Tool for probabilistically linking the records of individual entities (e.g. people) within and across datasets
Home-page: https://github.com/urban-labs/namematch
Author: University of Chicago Crime Lab
Author-email: mmcneill@uchicago.edu, tlin2@uchicago.edu, zjelveh@umd.edu
License: AGPL-3.0
Project-URL: Documentation, https://urban-labs.github.io/namematch/
Project-URL: Source Code, https://github.com/urban-labs/namematch
Keywords: record linkage
Classifier: Development Status :: 2 - Pre-Alpha
Classifier: Intended Audience :: Developers
Classifier: Natural Language :: English
Classifier: Programming Language :: Python :: 3
Classifier: Programming Language :: Python :: 3.7
Classifier: Programming Language :: Python :: 3.8
License-File: LICENSE
Requires-Dist: argcmdr (>=0.7.0)
Requires-Dist: networkx (==2.6.3)
Requires-Dist: pandas (==1.3.4)
Requires-Dist: numpy (>=1.20.1)
Requires-Dist: scikit-learn (==1.0.1)
Requires-Dist: pyyaml (==5.1)
Requires-Dist: ruamel.yaml (==0.17.17)
Requires-Dist: line-profiler (==3.3.1)
Requires-Dist: jellyfish (==0.8.9)
Requires-Dist: pyjarowinkler (==1.8)
Requires-Dist: editdistance (==0.6.0)
Requires-Dist: street-address (==0.4.0)
Requires-Dist: nmslib (<2.2,>=2.1.1)
Requires-Dist: coloredlogs (==14.0)
Requires-Dist: python-levenshtein (==0.12.2)
Requires-Dist: pyarrow (==7.0.0)
Requires-Dist: Dickens (>=1.0.1)
Requires-Dist: nbconvert (==6.5.2)
Requires-Dist: ipykernel (==6.16.0)
Requires-Dist: ipywidgets
Requires-Dist: papermill (==2.4.0)
Requires-Dist: memory-profiler (==0.60)
